mrok/__init__.py
mrok/conf.py
mrok/constants.py
mrok/errors.py
mrok/logging.py
mrok/agent/__init__.py
mrok/agent/ziticorn.py
mrok/agent/devtools/__init__.py
mrok/agent/devtools/inspector/__init__.py
mrok/agent/devtools/inspector/__main__.py
mrok/agent/devtools/inspector/app.py
mrok/agent/devtools/inspector/server.py
mrok/agent/devtools/inspector/utils.py
mrok/agent/sidecar/__init__.py
mrok/agent/sidecar/app.py
mrok/agent/sidecar/main.py
mrok/cli/__init__.py
mrok/cli/main.py
mrok/cli/rich.py
mrok/cli/utils.py
mrok/cli/commands/__init__.py
mrok/cli/commands/admin/__init__.py
mrok/cli/commands/admin/bootstrap.py
mrok/cli/commands/admin/utils.py
mrok/cli/commands/admin/list/__init__.py
mrok/cli/commands/admin/list/extensions.py
mrok/cli/commands/admin/list/instances.py
mrok/cli/commands/admin/register/__init__.py
mrok/cli/commands/admin/register/extensions.py
mrok/cli/commands/admin/register/instances.py
mrok/cli/commands/admin/unregister/__init__.py
mrok/cli/commands/admin/unregister/extensions.py
mrok/cli/commands/admin/unregister/instances.py
mrok/cli/commands/agent/__init__.py
mrok/cli/commands/agent/dev/__init__.py
mrok/cli/commands/agent/dev/console.py
mrok/cli/commands/agent/dev/web.py
mrok/cli/commands/agent/run/__init__.py
mrok/cli/commands/agent/run/asgi.py
mrok/cli/commands/agent/run/sidecar.py
mrok/cli/commands/controller/__init__.py
mrok/cli/commands/controller/openapi.py
mrok/cli/commands/controller/run.py
mrok/cli/commands/frontend/__init__.py
mrok/cli/commands/frontend/run.py
mrok/controller/__init__.py
mrok/controller/app.py
mrok/controller/auth.py
mrok/controller/pagination.py
mrok/controller/schemas.py
mrok/controller/dependencies/__init__.py
mrok/controller/dependencies/conf.py
mrok/controller/dependencies/ziti.py
mrok/controller/openapi/__init__.py
mrok/controller/openapi/examples.py
mrok/controller/openapi/utils.py
mrok/controller/routes/__init__.py
mrok/controller/routes/extensions.py
mrok/controller/routes/instances.py
mrok/frontend/__init__.py
mrok-0.7.0.dist-info/METADATA
mrok-0.7.0.dist-info/WHEEL
mrok-0.7.0.dist-info/entry_points.txt
mrok-0.7.0.dist-info/licenses/LICENSE.txt
mrok-0.7.0.dist-info/RECORD
