Metadata-Version: 2.4
Name: mrok
Version: 0.7.0
Summary: MPT Extensions OpenZiti Orchestrator
Author: SoftwareOne AG
License:                                  Apache License
License-File: LICENSE.txt
Requires-Python: <4,>=3.12
Requires-Dist: asn1crypto<2.0.0,>=1.5.1
Requires-Dist: cryptography<46.0.0,>=45.0.7
Requires-Dist: dynaconf<4.0.0,>=3.2.11
Requires-Dist: fastapi-pagination<0.15.0,>=0.14.1
Requires-Dist: fastapi[standard]<0.120.0,>=0.119.0
Requires-Dist: gunicorn<24.0.0,>=23.0.0
Requires-Dist: hdrhistogram<0.11.0,>=0.10.3
Requires-Dist: httpcore<2.0.0,>=1.0.9
Requires-Dist: multipart<2.0.0,>=1.3.0
Requires-Dist: openziti<2.0.0,>=1.3.1
Requires-Dist: psutil<8.0.0,>=7.1.3
Requires-Dist: pydantic<3.0.0,>=2.11.7
Requires-Dist: pyfiglet<2.0.0,>=1.0.4
Requires-Dist: pyjwt<3.0.0,>=2.10.1
Requires-Dist: pyyaml<7.0.0,>=6.0.2
Requires-Dist: pyzmq<28.0.0,>=27.1.0
Requires-Dist: rich<15.0.0,>=14.1.0
Requires-Dist: textual-serve<2.0.0,>=1.1.3
Requires-Dist: textual[syntax]<8.0.0,>=7.2.0
Requires-Dist: typer<0.20.0,>=0.19.2
Requires-Dist: uvicorn-worker<0.5.0,>=0.4.0
